mc_calculator/__init__.py
mc_calculator/__main__.py
mc_calculator/crafting_block.py
mc_calculator/database_ops.py
mc_calculator/decorator.py
mc_calculator/recipe.py
mc_calculator/recipe_logic.py
mc_calculator-0.3.2.dist-info/METADATA
mc_calculator-0.3.2.dist-info/WHEEL
mc_calculator-0.3.2.dist-info/entry_points.txt
mc_calculator-0.3.2.dist-info/top_level.txt
mc_calculator-0.3.2.dist-info/RECORD
