Metadata-Version: 2.1
Name: mc_calculator
Version: 0.3.2
Summary: A Minecraft recipe calculator
Home-page: https://github.com/nuclear-treestump/mc-calculator
Author: 0xIkari
Author-email: ikari@nuclear-treestump.com
Classifier: Programming Language :: Python :: 3.11
Classifier: Operating System :: OS Independent
Requires-Python: >=3.11
